{
  "adaptationDecision": {
    "status": "unchanged",
    "reason": "no future retargetable practice nodes remained",
    "source": {
      "ts": "2026-05-19T03:03:56.569Z",
      "sessionId": "c320d25c-0848-4222-b2c3-4e3b3d3361e3",
      "child": "Ila",
      "subject": "homework",
      "type": "next_plan_unchanged",
      "source": "map_coordinator",
      "childId": "demo_adaptive",
      "nodeId": "n-word-radar-hw-adapt-weak_performance",
      "activityId": "word-radar",
      "changedNodeIds": [],
      "skippedPracticeNodeIds": [],
      "nextTargets": [],
      "reason": "no future retargetable practice nodes remained"
    }
  }
}
