{
  "adaptationDecision": {
    "status": "unchanged",
    "reason": "no future retargetable practice nodes remained",
    "source": {
      "ts": "2026-05-19T05:16:08.046Z",
      "sessionId": "ca597d52-5b38-4b30-98b1-43ceec35ccf6",
      "child": "Ila",
      "subject": "homework",
      "type": "next_plan_unchanged",
      "source": "map_coordinator",
      "childId": "demo_adaptive",
      "nodeId": "n-word-radar-hw-adapt-weak_performance",
      "activityId": "word-radar",
      "changedNodeIds": [],
      "skippedPracticeNodeIds": [],
      "nextTargets": [],
      "reason": "no future retargetable practice nodes remained"
    }
  }
}
